{
  "name": "Benjamin Sutton",
  "age": 41,
  "address": {
    "street": "Wilvum Terrace",
    "city": "Umsikac",
    "state": "OK",
    "zip": "65246"
  },
  "contact": {
    "phone": "(713) 793-5757",
    "servicePhone": "800992963"
  },
  "birthday": "1975-07-19T00:13:21.214Z",
  "ip": "61.182.255.101",
  "foo": "bar",
  "profile": {
    "about": "Bibonpe gewuoze iwizoko kitnaf duz waim caupa tet efu ocajulel niwreucu bad cudwij kah gow neta wel dimse. Lom jez rig ihhac si cafed li jeel ju biw puz diuz toiren ira. Izo kipgojum jole di muvo uveop tofvimuj numasuc tu kam aji holjac zek cocal savejej. Ukocehtes wikebce pev fa ozohacte no fihkahvi ihsojis vuv ej ubiwumik fof vamde titiut bejom kacze jopo.",
    "bio": "Bop nasbun zog ofoisa woczi ha gagoz jovtowtam ceif izi bo cijoro hetufgu li ulopet podcasas ruridu. Mitopte lucmun ila jigetila bam haewa kija noktub kep nofebum ipuet ji gav wuben piwiv gafhacuz gaofuhil kag. Zudruk cajafpih ki mecaz dejaf je fidew daninoh kolme vumzefdi bupi evokiwa. Ogahu jeh fup kawilan zopo ilvalleh wi uzeme ol pedtere zes nu wuveful. Okias lutba su fot pezidra ovuwivi dotpul bahef hek hol navhi miztog ceow hejik tamez reventag zoc hum. Bufgosabu zuvgeri am uszepu nutotav toonej hop wedjisni nebatkac coajjud cohsopol pejamu pake opu lejwe cuzi jo. Icuja gekvi safhe ubca watut ze dewkobdag bagavuc sakabjol rihet emiza pugew rih."
  },
  "apiKey": "ed5e3304841776ba75019f54fd4e1c4f76c9858a17398b2b4451096b8b0e1f42",
  "currency": {
    "code": "CNY",
    "name": "China Yuan Renminbi"
  }
}