{
  "name": "Allie Bailey",
  "age": 53,
  "address": {
    "street": "Hihwip Avenue",
    "city": "Wekjatfup",
    "state": "RI",
    "zip": "71123"
  },
  "contact": {
    "phone": "(902) 627-5868",
    "servicePhone": "800638334"
  },
  "birthday": "1978-09-25T23:53:00.598Z",
  "ip": "163.101.88.13",
  "foo": "bar",
  "profile": {
    "about": "Kemab jihcu viizuki ok ganid nejgir gouwme ibubuwlon azacukbe nof sew avwif iv topon. Vusoz gev bic ap pe lomesih juef jo reshieci sawag tiwhiub ha kunma tuhuopi owiezli pozopol dedneb. Gas wumre riggak hi ob pukate zoztueni of mugkas ru zuk do hagehpa paguhjok fapfazim.",
    "bio": "Abiwujseg retarez dedtel rabokri cumuk ocwoziw namma fat pawko toluir iri ni dizesobo tudebpa jeksuh. Mimu cuhamro bunkotip it gi dout del pappozpoz duuwa jozep he nowiw ozekat gontattov is potfiwnah da uzifeog. Zow hoj ninte hawo vem gak zehofac pe nep eguso vaed gi eftum ec. Pibun amjidbej soguvef es legabbo nenaf dipfaf focizuf ser wuzoaf wu an momnu vek ji folej. Muwsoca ce uguubke mobib nul gifejob otjase deepnic fafolupaw omoribsa nicittef ri nicpeza kiuzowo tuleb pipibeme re fijove. Ubfom moperhus ag uco icsoki bikdo ehdapjav piszidev rorgu ujomout gehinzep zuro kiwdot pojuhocot."
  },
  "apiKey": "b9f1670a425536134ac9c5a911882ed9eac00d9a9b9ada62add73d5f0340951d",
  "currency": {
    "code": "CZK",
    "name": "Czech Republic Koruna"
  }
}